{
  "minecraft:recipes/decorations/crafting_table": {
    "criteria": {
      "unlock_right_away": "2025-05-17 21:29:16 +0000"
    },
    "done": true
  },
  "minecraft:adventure/adventuring_time": {
    "criteria": {
      "minecraft:frozen_river": "2025-05-17 21:35:08 +0000",
      "minecraft:snowy_plains": "2025-05-17 21:29:18 +0000",
      "minecraft:ice_spikes": "2025-05-17 21:35:09 +0000",
      "minecraft:snowy_beach": "2025-05-18 08:56:43 +0000",
      "minecraft:plains": "2025-05-17 21:40:36 +0000"
    },
    "done": false
  },
  "minecraft:adventure/root": {
    "criteria": {
      "killed_by_something": "2025-05-17 21:30:50 +0000"
    },
    "done": true
  },
  "minecraft:recipes/misc/flower_banner_pattern": {
    "criteria": {
      "has_oxeye_daisy": "2025-05-17 21:48:00 +0000"
    },
    "done": true
  },
  "minecraft:recipes/misc/light_gray_dye_from_oxeye_daisy": {
    "criteria": {
      "has_oxeye_daisy": "2025-05-17 21:48:00 +0000"
    },
    "done": true
  },
  "minecraft:adventure/kill_all_mobs": {
    "criteria": {
      "minecraft:creeper": "2025-05-17 22:02:51 +0000"
    },
    "done": false
  },
  "minecraft:adventure/kill_a_mob": {
    "criteria": {
      "minecraft:creeper": "2025-05-17 22:02:51 +0000"
    },
    "done": true
  },
  "minecraft:recipes/misc/firework_rocket_simple": {
    "criteria": {
      "has_gunpowder": "2025-05-17 22:02:51 +0000"
    },
    "done": true
  },
  "minecraft:recipes/redstone/tnt": {
    "criteria": {
      "has_gunpowder": "2025-05-17 22:02:51 +0000"
    },
    "done": true
  },
  "minecraft:recipes/misc/charcoal": {
    "criteria": {
      "has_log": "2025-05-18 08:47:38 +0000"
    },
    "done": true
  },
  "minecraft:recipes/building_blocks/oak_planks": {
    "criteria": {
      "has_logs": "2025-05-18 08:47:38 +0000"
    },
    "done": true
  },
  "minecraft:recipes/building_blocks/stripped_oak_wood": {
    "criteria": {
      "has_log": "2025-05-18 08:47:38 +0000"
    },
    "done": true
  },
  "minecraft:recipes/decorations/oak_hanging_sign": {
    "criteria": {
      "has_stripped_logs": "2025-05-18 08:47:38 +0000"
    },
    "done": true
  },
  "minecraft:adventure/sleep_in_bed": {
    "criteria": {
      "slept_in_bed": "2025-05-18 09:01:58 +0000"
    },
    "done": true
  },
  "minecraft:recipes/decorations/campfire": {
    "criteria": {
      "has_coal": "2025-05-18 09:03:24 +0000"
    },
    "done": true
  },
  "minecraft:recipes/building_blocks/coal_block": {
    "criteria": {
      "has_coal": "2025-05-18 09:03:24 +0000"
    },
    "done": true
  },
  "minecraft:recipes/food/baked_potato_from_campfire_cooking": {
    "criteria": {
      "has_potato": "2025-05-18 09:03:29 +0000"
    },
    "done": true
  },
  "minecraft:recipes/food/baked_potato_from_smoking": {
    "criteria": {
      "has_potato": "2025-05-18 09:03:29 +0000"
    },
    "done": true
  },
  "minecraft:recipes/food/baked_potato": {
    "criteria": {
      "has_potato": "2025-05-18 09:03:29 +0000"
    },
    "done": true
  },
  "minecraft:recipes/transportation/mangrove_boat": {
    "criteria": {
      "in_water": "2025-05-18 09:15:46 +0000"
    },
    "done": true
  },
  "minecraft:recipes/transportation/carrot_on_a_stick": {
    "criteria": {
      "has_carrot": "2025-05-18 09:15:48 +0000"
    },
    "done": true
  },
  "minecraft:recipes/transportation/acacia_boat": {
    "criteria": {
      "in_water": "2025-05-18 09:15:46 +0000"
    },
    "done": true
  },
  "minecraft:recipes/transportation/cherry_boat": {
    "criteria": {
      "in_water": "2025-05-18 09:15:46 +0000"
    },
    "done": true
  },
  "minecraft:recipes/transportation/bamboo_raft": {
    "criteria": {
      "in_water": "2025-05-18 09:15:46 +0000"
    },
    "done": true
  },
  "minecraft:recipes/transportation/spruce_boat": {
    "criteria": {
      "in_water": "2025-05-18 09:15:46 +0000"
    },
    "done": true
  },
  "minecraft:husbandry/balanced_diet": {
    "criteria": {
      "carrot": "2025-05-18 09:15:50 +0000"
    },
    "done": false
  },
  "minecraft:husbandry/root": {
    "criteria": {
      "consumed_item": "2025-05-18 09:15:50 +0000"
    },
    "done": true
  },
  "minecraft:recipes/transportation/birch_boat": {
    "criteria": {
      "in_water": "2025-05-18 09:15:46 +0000"
    },
    "done": true
  },
  "minecraft:recipes/transportation/oak_boat": {
    "criteria": {
      "in_water": "2025-05-18 09:15:46 +0000"
    },
    "done": true
  },
  "minecraft:recipes/transportation/jungle_boat": {
    "criteria": {
      "in_water": "2025-05-18 09:15:46 +0000"
    },
    "done": true
  },
  "minecraft:recipes/transportation/dark_oak_boat": {
    "criteria": {
      "in_water": "2025-05-18 09:15:46 +0000"
    },
    "done": true
  },
  "DataVersion": 3465
}