{"stats":{"minecraft:custom":{"minecraft:jump":484,"minecraft:time_since_rest":48830,"minecraft:damage_taken":1245,"minecraft:leave_game":3,"minecraft:play_time":79727,"minecraft:walk_one_cm":1531410,"minecraft:time_since_death":48826,"minecraft:deaths":4,"minecraft:total_world_time":79727,"minecraft:fly_one_cm":36575,"minecraft:fall_one_cm":406},"minecraft:picked_up":{"minecraft:snowball":18,"minecraft:dirt":16},"minecraft:killed_by":{"minecraft:zombie":2,"minecraft:creeper":1,"minecraft:spider":1}},"DataVersion":3465}