{"stats":{"minecraft:custom":{"minecraft:jump":537,"minecraft:time_since_rest":16084,"minecraft:damage_dealt":67,"minecraft:damage_taken":1875,"minecraft:play_time":107923,"minecraft:leave_game":9,"minecraft:sprint_one_cm":19721,"minecraft:walk_one_cm":1587501,"minecraft:time_since_death":16077,"minecraft:deaths":7,"minecraft:total_world_time":107923,"minecraft:mob_kills":1,"minecraft:fly_one_cm":46555,"minecraft:fall_one_cm":3883},"minecraft:killed":{"minecraft:spider":1},"minecraft:mined":{"minecraft:dirt":5},"minecraft:killed_by":{"minecraft:zombie":4,"minecraft:player":1,"minecraft:spider":1},"minecraft:picked_up":{"minecraft:snowball":31,"minecraft:string":2,"minecraft:dirt":50}},"DataVersion":3465}